Metadata-Version: 2.1
Name: filemi
Version: 1.0
Summary: A file management utility package
Author: Your Name
Author-email: dillon.nyxlyn@gmail.com
License-File: LICENSE
